srme/__init__.py
srme/core.py
srme/metrics.py
srme/savers/__init__.py
srme/savers/csv_saver.py
srme/savers/mlflow_saver.py
srme/trackers.py
srme-0.1.1.dist-info/LICENSE
srme-0.1.1.dist-info/METADATA
srme-0.1.1.dist-info/WHEEL
srme-0.1.1.dist-info/RECORD
