Metadata-Version: 2.1
Name: srme
Version: 0.1.1
Summary: System Resource Monitor for Experiments
Home-page: https://github.com/IKaftanov/srme
Author: Ilya Kaftanov
Author-email: kaftanovwork@gmail.com
Requires-Python: >=3.9,<4.0
Classifier: Programming Language :: Python :: 3
Classifier: Programming Language :: Python :: 3.9
Classifier: Programming Language :: Python :: 3.10
Classifier: Programming Language :: Python :: 3.11
Classifier: Programming Language :: Python :: 3.12
Provides-Extra: mlflow
Requires-Dist: mlflow (>=2.11.1,<3.0.0) ; extra == "mlflow"
Requires-Dist: psutil (>=5.9.8,<6.0.0)
